{
    "version": "1.25.0",
    "architecture": {
        "32bit": {
            "url": "https://github.com/miniscruff/changie/releases/download/v1.25.0/changie_1.25.0_windows_386.zip",
            "bin": [
                "changie.exe"
            ],
            "hash": "424566675172bef73840f3ce465208e3b1de5a74a6383260e058b15cb4985bec"
        },
        "64bit": {
            "url": "https://github.com/miniscruff/changie/releases/download/v1.25.0/changie_1.25.0_windows_amd64.zip",
            "bin": [
                "changie.exe"
            ],
            "hash": "504958fd7ece0303a2ef876ecc3bd60903f0e4f8cda008117683b8ed4ff97d38"
        },
        "arm64": {
            "url": "https://github.com/miniscruff/changie/releases/download/v1.25.0/changie_1.25.0_windows_arm64.zip",
            "bin": [
                "changie.exe"
            ],
            "hash": "fd04b88c6eba08c81e71920c9423d1adc2e988cb000197ee84a6fdd5802efc6e"
        }
    },
    "homepage": "https://changie.dev",
    "license": "MIT",
    "description": "Automated changelog tool for preparing releases with lots of customization options."
}
